Workbook

Sheet Presupuesto
A1: Presupuesto reparto cajas navideñas – Foton (pesos, sin IVA)
A3: Esquema recomendado: 3 viajes
A4: Código | B4: Viaje | C4: Cajas | D4: Km totales | E4: Días extra (paradas) | F4: Días totales | G4: Gasoil | H4: Cubiertas y mant. | I4: Amort. y seguro | J4: Chofer (sueldo + viático) | K4: Peajes | L4: Costo total | M4: Costo $/km | N4: Precio mínimo | O4: Precio máximo | P4: Precio medio | Q4: Precio medio por caja
A5: V1 | B5: Costa, Sur y Cuyo | C5: =SUMIFS(Destinos!$C$2:$C$31,Destinos!$D$2:$D$31,A5) -> 36 | D5: =SUMIFS(Tramos!$D$2:$D$39,Tramos!$A$2:$A$39,A5) -> 3600 | E5: 1 | F5: =ROUNDUP(D5/Supuestos!$B$12,0)+E5 -> 7 | G5: =D5*Supuestos!$B$6/100*Supuestos!$B$5 -> 1346400 | H5: =D5*Supuestos!$B$7 -> 540000 | I5: =D5*Supuestos!$B$8 -> 720000 | J5: =F5*(Supuestos!$B$10+Supuestos!$B$11) -> 1470000 | K5: =D5*Supuestos!$B$9 -> 72000 | L5: =SUM(G5:K5) -> 4148400 | M5: =IF(D5=0,0,L5/D5) -> 1152.3333 | N5: =L5*(1+Supuestos!$B$13) -> 5807760 | O5: =L5*(1+Supuestos!$B$14) -> 8296800 | P5: =AVERAGE(N5:O5) -> 7052280 | Q5: =IF(C5=0,0,P5/C5) -> 195896.67
A6: V2 | B6: Litoral y NEA | C6: =SUMIFS(Destinos!$C$2:$C$31,Destinos!$D$2:$D$31,A6) -> 17 | D6: =SUMIFS(Tramos!$D$2:$D$39,Tramos!$A$2:$A$39,A6) -> 2610 | E6: 0 | F6: =ROUNDUP(D6/Supuestos!$B$12,0)+E6 -> 5 | G6: =D6*Supuestos!$B$6/100*Supuestos!$B$5 -> 976140 | H6: =D6*Supuestos!$B$7 -> 391500 | I6: =D6*Supuestos!$B$8 -> 522000 | J6: =F6*(Supuestos!$B$10+Supuestos!$B$11) -> 1050000 | K6: =D6*Supuestos!$B$9 -> 52200 | L6: =SUM(G6:K6) -> 2991840 | M6: =IF(D6=0,0,L6/D6) -> 1146.2989 | N6: =L6*(1+Supuestos!$B$13) -> 4188576 | O6: =L6*(1+Supuestos!$B$14) -> 5983680 | P6: =AVERAGE(N6:O6) -> 5086128 | Q6: =IF(C6=0,0,P6/C6) -> 299184
A7: V3 | B7: NOA | C7: =SUMIFS(Destinos!$C$2:$C$31,Destinos!$D$2:$D$31,A7) -> 13 | D7: =SUMIFS(Tramos!$D$2:$D$39,Tramos!$A$2:$A$39,A7) -> 3350 | E7: 0 | F7: =ROUNDUP(D7/Supuestos!$B$12,0)+E7 -> 6 | G7: =D7*Supuestos!$B$6/100*Supuestos!$B$5 -> 1252900 | H7: =D7*Supuestos!$B$7 -> 502500 | I7: =D7*Supuestos!$B$8 -> 670000 | J7: =F7*(Supuestos!$B$10+Supuestos!$B$11) -> 1260000 | K7: =D7*Supuestos!$B$9 -> 67000 | L7: =SUM(G7:K7) -> 3752400 | M7: =IF(D7=0,0,L7/D7) -> 1120.1194 | N7: =L7*(1+Supuestos!$B$13) -> 5253360 | O7: =L7*(1+Supuestos!$B$14) -> 7504800 | P7: =AVERAGE(N7:O7) -> 6379080 | Q7: =IF(C7=0,0,P7/C7) -> 490698.46
B8: TOTAL | C8: =SUM(C5:C7) -> 66 | D8: =SUM(D5:D7) -> 9560 | F8: =SUM(F5:F7) -> 18 | G8: =SUM(G5:G7) -> 3575440 | H8: =SUM(H5:H7) -> 1434000 | I8: =SUM(I5:I7) -> 1912000 | J8: =SUM(J5:J7) -> 3780000 | K8: =SUM(K5:K7) -> 191200 | L8: =SUM(L5:L7) -> 10892640 | M8: =IF(D8=0,0,L8/D8) -> 1139.3975 | N8: =SUM(N5:N7) -> 15249696 | O8: =SUM(O5:O7) -> 21785280 | P8: =SUM(P5:P7) -> 18517488 | Q8: =IF(C8=0,0,P8/C8) -> 280568
A11: Alternativa: 2 viajes
A12: Código | B12: Viaje | C12: Cajas | D12: Km totales | E12: Días extra (paradas) | F12: Días totales | G12: Gasoil | H12: Cubiertas y mant. | I12: Amort. y seguro | J12: Chofer (sueldo + viático) | K12: Peajes | L12: Costo total | M12: Costo $/km | N12: Precio mínimo | O12: Precio máximo | P12: Precio medio | Q12: Precio medio por caja
A13: V1 | B13: Costa, Sur y Cuyo | C13: =SUMIFS(Destinos!$C$2:$C$31,Destinos!$E$2:$E$31,A13) -> 36 | D13: =SUMIFS(Tramos!$D$2:$D$39,Tramos!$A$2:$A$39,A13) -> 3600 | E13: 1 | F13: =ROUNDUP(D13/Supuestos!$B$12,0)+E13 -> 7 | G13: =D13*Supuestos!$B$6/100*Supuestos!$B$5 -> 1346400 | H13: =D13*Supuestos!$B$7 -> 540000 | I13: =D13*Supuestos!$B$8 -> 720000 | J13: =F13*(Supuestos!$B$10+Supuestos!$B$11) -> 1470000 | K13: =D13*Supuestos!$B$9 -> 72000 | L13: =SUM(G13:K13) -> 4148400 | M13: =IF(D13=0,0,L13/D13) -> 1152.3333 | N13: =L13*(1+Supuestos!$B$13) -> 5807760 | O13: =L13*(1+Supuestos!$B$14) -> 8296800 | P13: =AVERAGE(N13:O13) -> 7052280 | Q13: =IF(C13=0,0,P13/C13) -> 195896.67
A14: VB | B14: Litoral + NEA + NOA | C14: =SUMIFS(Destinos!$C$2:$C$31,Destinos!$E$2:$E$31,A14) -> 30 | D14: =SUMIFS(Tramos!$D$2:$D$39,Tramos!$A$2:$A$39,A14) -> 4330 | E14: 1 | F14: =ROUNDUP(D14/Supuestos!$B$12,0)+E14 -> 9 | G14: =D14*Supuestos!$B$6/100*Supuestos!$B$5 -> 1619420 | H14: =D14*Supuestos!$B$7 -> 649500 | I14: =D14*Supuestos!$B$8 -> 866000 | J14: =F14*(Supuestos!$B$10+Supuestos!$B$11) -> 1890000 | K14: =D14*Supuestos!$B$9 -> 86600 | L14: =SUM(G14:K14) -> 5111520 | M14: =IF(D14=0,0,L14/D14) -> 1180.4896 | N14: =L14*(1+Supuestos!$B$13) -> 7156128 | O14: =L14*(1+Supuestos!$B$14) -> 10223040 | P14: =AVERAGE(N14:O14) -> 8689584 | Q14: =IF(C14=0,0,P14/C14) -> 289652.8
B15: TOTAL | C15: =SUM(C13:C14) -> 66 | D15: =SUM(D13:D14) -> 7930 | F15: =SUM(F13:F14) -> 16 | G15: =SUM(G13:G14) -> 2965820 | H15: =SUM(H13:H14) -> 1189500 | I15: =SUM(I13:I14) -> 1586000 | J15: =SUM(J13:J14) -> 3360000 | K15: =SUM(K13:K14) -> 158600 | L15: =SUM(L13:L14) -> 9259920 | M15: =IF(D15=0,0,L15/D15) -> 1167.7074 | N15: =SUM(N13:N14) -> 12963888 | O15: =SUM(O13:O14) -> 18519840 | P15: =SUM(P13:P14) -> 15741864 | Q15: =IF(C15=0,0,P15/C15) -> 238513.09
A17: Cómo usar: editá los supuestos (hoja Supuestos), los km (hoja Tramos) o los días extra por paradas (columna E, amarillo).
A18: Cajas: se toman de la hoja Destinos según el código de viaje. Rafaela (Cortassa) está a definir: si se cae, poné 0 cajas y sacá el desvío en Tramos.
A19: Días totales = días de manejo (km ÷ km por día, redondeado para arriba) + días extra por paradas (p. ej., un día completo en Neuquén).
A20: Precio mínimo / máximo = costo × (1 + margen). El precio medio es el valor sugerido para presupuestar. No incluye IVA.

Sheet Supuestos
A1: Presupuesto reparto cajas navideñas – Foton
A2: Celdas en azul con fondo amarillo = supuestos editables. Todo lo demás se calcula solo. Valores en pesos, sin IVA.
A4: Supuesto | B4: Valor | C4: Unidad | D4: Fuente / comentario
A5: Precio gasoil | B5: 2200 | C5: $/litro | D5: YPF CABA ~$2.176/L desde 26/09/2026 (naftahoy.com / La Nación). Actualizar con precio del día.
A6: Consumo Foton | B6: 17 | C6: litros/100 km | D6: Estimado camión liviano cargado. Reemplazar por consumo real.
A7: Cubiertas, mantenimiento y lubricantes | B7: 150 | C7: $/km | D7: Estimado propio.
A8: Amortización, seguro y patente | B8: 200 | C8: $/km | D8: Estimado propio. Reemplazar por costo real del Foton.
A9: Peajes | B9: 20 | C9: $/km | D9: Estimado propio promedio por km.
A10: Sueldo chofer con cargas sociales | B10: 130000 | C10: $/día | D10: Estimado propio. Reemplazar por costo real.
A11: Viáticos chofer (comida + alojamiento) | B11: 80000 | C11: $/día | D11: Estimado propio.
A12: Km recorridos por día | B12: 600 | C12: km/día | D12: Ruta + repartos urbanos.
A13: Margen mínimo sobre costo | B13: 0.4 | C13: % | D13: Precio piso.
A14: Margen máximo sobre costo | B14: 1 | C14: % | D14: Precio techo. Mercado minifletes ~$1.870–2.500/km (cargasxl.com, 06/2026).
A17: Nota: el costo de transporte subió ~41% interanual (índice FADEEAC, sep-2026). Revisar supuestos si el presupuesto se aprueba más adelante.

Sheet Destinos
A1: Provincia / Zona | B1: Dirección | C1: Cajas | D1: Viaje (esquema 3 viajes) | E1: Viaje (esquema 2 viajes)
A2: Bahía Blanca | B2: Alsina 144 | C2: 1 | D2: V1 | E2: V1
A3: Bahía Blanca | B3: O Higgins 51 | C3: 1 | D3: V1 | E3: V1
A4: Bahía Blanca | B4: Sarmiento 2153 | C4: 2 | D4: V1 | E4: V1
A5: Catamarca | B5: Av. Pres. Arturo Illia 997, SF del Valle de Catamarca | C5: 1 | D5: V3 | E5: VB
A6: Chaco | B6: CBC, Güemes 165, Resistencia | C6: 3 | D6: V2 | E6: VB
A7: Entre Ríos | B7: Gral. José de San Martín 1071, Paraná | C7: 2 | D7: V2 | E7: VB
A8: Formosa | B8: España 112, Formosa | C8: 2 | D8: V2 | E8: VB
A9: Jujuy | B9: ABI, Gral. Belgrano 563, San Salvador de Jujuy | C9: 2 | D9: V3 | E9: VB
A10: Mar del Plata | B10: Castelli 1309 esq. Güemes | C10: 1 | D10: V1 | E10: V1
A11: Mar del Plata | B11: Sarmiento 2685 | C11: 2 | D11: V1 | E11: V1
A12: Mendoza | B12: Av. San Martín 1229 (Julieriaque Mendoza Centro) | C12: 1 | D12: V1 | E12: V1
A13: Mendoza | B13: Av. San Martín Sur 2875, Godoy Cruz (Palmares Shopping) | C13: 4 | D13: V1 | E13: V1
... A31: Tucumán | B31: Cariola 42, San Miguel de Tucumán (Portal Tucumán) | C31: 3 | D31: V3 | E31: VB
A32: TOTAL | C32: =SUM(C2:C31) -> 66
A34: Podés mover un destino de viaje cambiando el código en las columnas D/E (V1, V2, V3, VB).

Sheet Tramos
A1: Viaje | B1: Desde | C1: Hasta | D1: Km
A2: V1 | B2: CABA | C2: Mar del Plata | D2: 400
A3: V1 | B3: Mar del Plata | C3: Bahía Blanca | D3: 470
A4: V1 | B4: Bahía Blanca | C4: Neuquén | D4: 540
A5: V1 | B5: Neuquén | C5: Cipolletti | D5: 15
A6: V1 | B6: Cipolletti | C6: Mendoza | D6: 800
A7: V1 | B7: Mendoza | C7: San Juan | D7: 170
A8: V1 | B8: San Juan | C8: CABA | D8: 1140
A9: V1 | B9: Repartos urbanos | C9: (todas las ciudades) | D9: 65
A10: V2 | B10: CABA | C10: Rosario | D10: 300
A11: V2 | B11: Rosario | C11: Rafaela | D11: 230
A12: V2 | B12: Rafaela | C12: Esperanza | D12: 70
A13: V2 | B13: Esperanza | C13: Santa Fe | D13: 40
... A39: VB | B39: Repartos urbanos | C39: (todas las ciudades) | D39: 80
A41: Km por ruta estimados (aprox.). Reemplazá con los de tu ruteo real; el presupuesto se recalcula solo.
